pyfreedb/__init__.py
pyfreedb/base.py
pyfreedb/codec.py
pyfreedb/kv/__init__.py
pyfreedb/kv/base.py
pyfreedb/kv/gsheet.py
pyfreedb/providers/__init__.py
pyfreedb/providers/google/__init__.py
pyfreedb/providers/google/auth/__init__.py
pyfreedb/providers/google/auth/base.py
pyfreedb/providers/google/auth/oauth.py
pyfreedb/providers/google/auth/service_account.py
pyfreedb/providers/google/sheet/__init__.py
pyfreedb/providers/google/sheet/base.py
pyfreedb/providers/google/sheet/wrapper.py
pyfreedb/row/__init__.py
pyfreedb/row/base.py
pyfreedb/row/gsheet.py
pyfreedb/row/models.py
pyfreedb/row/query_builder.py
pyfreedb/row/stmt.py
pyfreedb-1.0.4.dist-info/LICENSE
pyfreedb-1.0.4.dist-info/WHEEL
pyfreedb-1.0.4.dist-info/METADATA
pyfreedb-1.0.4.dist-info/RECORD
