Metadata-Version: 2.3
Name: pyfreedb
Version: 1.0.4
Summary: PyFreeDB is a Python library that provides common and simple database abstractions on top of Google Sheets.
Author-email: Edwin Candinegara <edwin.candinegara@gmail.com>, Fata Nugraha <fatanugraha@outlook.com>
Requires-Python: >=3.7
Classifier: License :: OSI Approved :: MIT License
Requires-Dist: google-api-python-client==2.51.0
Requires-Dist: google-auth-httplib2==0.1.0
Requires-Dist: google-auth-oauthlib==0.5.2
Requires-Dist: requests>=2.28.1, < 3
Requires-Dist: pdoc3 ; extra == "doc"
Requires-Dist: black==24.10.0 ; extra == "test"
Requires-Dist: mypy==0.961 ; extra == "test"
Requires-Dist: isort==5.10.1 ; extra == "test"
Requires-Dist: pytest==7.1.2 ; extra == "test"
Requires-Dist: autoflake==2.3.1 ; extra == "test"
Requires-Dist: types-requests==2.28.6 ; extra == "test"
Requires-Dist: coverage==6.4.4 ; extra == "test"
Project-URL: Home, https://github.com/FreeLeh/PyFreeDB
Provides-Extra: doc
Provides-Extra: test
